
{"page":{"@id":"2016","@guid":"1f9cac3bc8914c3e99b0e19568542c9b","@draft.state":"inactive","@href":"https://efm-sandbox.mindtouch.us/@api/deki/pages/2016?redirects=0","@deleted":"false","date.created":"Sat, 04 Mar 2017 08:23:01 GMT","language":"en-US","namespace":"main","path":{"@seo":"true","#text":"Compuware1"},"subpages":{"page":[{"@id":"2018","@guid":"6491f8cd68014f8ea27df7cf845c0281","@draft.state":"inactive","@href":"https://efm-sandbox.mindtouch.us/@api/deki/pages/2018?redirects=0","@deleted":"false","date.created":"Sat, 04 Mar 2017 08:42:33 GMT","language":"en-US","namespace":"main","path":{"@seo":"true","#text":"Compuware1/Introduction"},"subpages":{"page":[{"@id":"2031","@guid":"f9b643c7bb14410eb42b9af2ea7c1d1f","@draft.state":"inactive","@href":"https://efm-sandbox.mindtouch.us/@api/deki/pages/2031?redirects=0","@deleted":"false","date.created":"Sat, 04 Mar 2017 08:56:44 GMT","language":"en-US","namespace":"main","path":{"@seo":"true","#text":"Compuware1/Introduction/Getting_Help"},"subpages":{"page":[{"@id":"2054","@guid":"87d49792b8074c2c99175da5f21b2c04","@draft.state":"inactive","@href":"https://efm-sandbox.mindtouch.us/@api/deki/pages/2054?redirects=0","@deleted":"false","date.created":"Sat, 04 Mar 2017 09:48:49 GMT","language":"en-US","namespace":"main","path":{"@seo":"true","#text":"Compuware1/Introduction/Getting_Help/Abend-AID_Customer_Support"},"subpages":"","title":"Abend-AID Customer Support","uri.ui":"https://efm-sandbox.mindtouch.us/Compuware1/Introduction/Getting_Help/Abend-AID_Customer_Support"},{"@id":"2034","@guid":"63a8bcb1b1b94056abf0182e2ec771bc","@draft.state":"inactive","@href":"https://efm-sandbox.mindtouch.us/@api/deki/pages/2034?redirects=0","@deleted":"false","date.created":"Sat, 04 Mar 2017 09:37:42 GMT","language":"en-US","namespace":"main","path":{"@seo":"true","#text":"Compuware1/Introduction/Getting_Help/Compuware_FrontLine_Customer_Support_Website"},"subpages":"","title":"Compuware FrontLine Customer Support Website","uri.ui":"https://efm-sandbox.mindtouch.us/Compuware1/Introduction/Getting_Help/Compuware_FrontLine_Customer_Support_Website"},{"@id":"2037","@guid":"e08d9196fdcd4f3b8f380599c88964cd","@draft.state":"inactive","@href":"https://efm-sandbox.mindtouch.us/@api/deki/pages/2037?redirects=0","@deleted":"false","date.created":"Sat, 04 Mar 2017 09:39:21 GMT","language":"en-US","namespace":"main","path":{"@seo":"true","#text":"Compuware1/Introduction/Getting_Help/Contacting_Customer_Support"},"subpages":{"page":[{"@id":"2045","@guid":"5b5c220c373a46b28166ce4492832985","@draft.state":"inactive","@href":"https://efm-sandbox.mindtouch.us/@api/deki/pages/2045?redirects=0","@deleted":"false","date.created":"Sat, 04 Mar 2017 09:43:28 GMT","language":"en-US","namespace":"main","path":{"@seo":"true","#text":"Compuware1/Introduction/Getting_Help/Contacting_Customer_Support/Mail"},"subpages":"","title":"Mail","uri.ui":"https://efm-sandbox.mindtouch.us/Compuware1/Introduction/Getting_Help/Contacting_Customer_Support/Mail"},{"@id":"2040","@guid":"561cf627a8c2481e8ce5fb5a39c0e41f","@draft.state":"inactive","@href":"https://efm-sandbox.mindtouch.us/@api/deki/pages/2040?redirects=0","@deleted":"false","date.created":"Sat, 04 Mar 2017 09:41:11 GMT","language":"en-US","namespace":"main","path":{"@seo":"true","#text":"Compuware1/Introduction/Getting_Help/Contacting_Customer_Support/Phone"},"subpages":"","title":"Phone","uri.ui":"https://efm-sandbox.mindtouch.us/Compuware1/Introduction/Getting_Help/Contacting_Customer_Support/Phone"},{"@id":"2042","@guid":"565a3d1236e243658324113dbf7680e4","@draft.state":"inactive","@href":"https://efm-sandbox.mindtouch.us/@api/deki/pages/2042?redirects=0","@deleted":"false","date.created":"Sat, 04 Mar 2017 09:42:27 GMT","language":"en-US","namespace":"main","path":{"@seo":"true","#text":"Compuware1/Introduction/Getting_Help/Contacting_Customer_Support/Web"},"subpages":"","title":"Web","uri.ui":"https://efm-sandbox.mindtouch.us/Compuware1/Introduction/Getting_Help/Contacting_Customer_Support/Web"}]},"title":"Contacting Customer Support","uri.ui":"https://efm-sandbox.mindtouch.us/Compuware1/Introduction/Getting_Help/Contacting_Customer_Support"},{"@id":"2048","@guid":"0c4b0676158248d6a5b3cfd8729a4b21","@draft.state":"inactive","@href":"https://efm-sandbox.mindtouch.us/@api/deki/pages/2048?redirects=0","@deleted":"false","date.created":"Sat, 04 Mar 2017 09:45:01 GMT","language":"en-US","namespace":"main","path":{"@seo":"true","#text":"Compuware1/Introduction/Getting_Help/Corporate_Website"},"subpages":"","title":"Corporate Website","uri.ui":"https://efm-sandbox.mindtouch.us/Compuware1/Introduction/Getting_Help/Corporate_Website"},{"@id":"2051","@guid":"9eb90891121245d5a842e0b174806f7a","@draft.state":"inactive","@href":"https://efm-sandbox.mindtouch.us/@api/deki/pages/2051?redirects=0","@deleted":"false","date.created":"Sat, 04 Mar 2017 09:46:29 GMT","language":"en-US","namespace":"main","path":{"@seo":"true","#text":"Compuware1/Introduction/Getting_Help/Online_Documentation"},"subpages":"","title":"Online Documentation","uri.ui":"https://efm-sandbox.mindtouch.us/Compuware1/Introduction/Getting_Help/Online_Documentation"}]},"title":"Getting Help","uri.ui":"https://efm-sandbox.mindtouch.us/Compuware1/Introduction/Getting_Help"},{"@id":"2020","@guid":"eade9cd1d88b4f1db0ad1a127ef35481","@draft.state":"inactive","@href":"https://efm-sandbox.mindtouch.us/@api/deki/pages/2020?redirects=0","@deleted":"false","date.created":"Sat, 04 Mar 2017 08:46:12 GMT","language":"en-US","namespace":"main","path":{"@seo":"true","#text":"Compuware1/Introduction/Intended_Audience"},"subpages":"","title":"Intended Audience","uri.ui":"https://efm-sandbox.mindtouch.us/Compuware1/Introduction/Intended_Audience"},{"@id":"2023","@guid":"b68bab6ff58b41edafd3e38a3b3cc580","@draft.state":"inactive","@href":"https://efm-sandbox.mindtouch.us/@api/deki/pages/2023?redirects=0","@deleted":"false","date.created":"Sat, 04 Mar 2017 08:48:26 GMT","language":"en-US","namespace":"main","path":{"@seo":"true","#text":"Compuware1/Introduction/Related_Publications"},"subpages":{"page":[{"@id":"2028","@guid":"4f725071d12d462a9acbbee314117d57","@draft.state":"inactive","@href":"https://efm-sandbox.mindtouch.us/@api/deki/pages/2028?redirects=0","@deleted":"false","date.created":"Sat, 04 Mar 2017 08:54:15 GMT","language":"en-US","namespace":"main","path":{"@seo":"true","#text":"Compuware1/Introduction/Related_Publications/IBM_Documentation"},"subpages":"","title":"IBM Documentation","uri.ui":"https://efm-sandbox.mindtouch.us/Compuware1/Introduction/Related_Publications/IBM_Documentation"},{"@id":"2026","@guid":"07ca691fd72a4454984edfdedab8eb1b","@draft.state":"inactive","@href":"https://efm-sandbox.mindtouch.us/@api/deki/pages/2026?redirects=0","@deleted":"false","date.created":"Sat, 04 Mar 2017 08:52:41 GMT","language":"en-US","namespace":"main","path":{"@seo":"true","#text":"Compuware1/Introduction/Related_Publications/Online_Help"},"subpages":"","title":"Online Help","uri.ui":"https://efm-sandbox.mindtouch.us/Compuware1/Introduction/Related_Publications/Online_Help"}]},"title":"Related Publications","uri.ui":"https://efm-sandbox.mindtouch.us/Compuware1/Introduction/Related_Publications"}]},"title":"Introduction","uri.ui":"https://efm-sandbox.mindtouch.us/Compuware1/Introduction"},{"@id":"2057","@guid":"2fee9a5c5a78473da6183166717d5220","@draft.state":"inactive","@href":"https://efm-sandbox.mindtouch.us/@api/deki/pages/2057?redirects=0","@deleted":"false","date.created":"Sat, 04 Mar 2017 09:54:05 GMT","language":"en-US","namespace":"main","path":{"@seo":"true","#text":"Compuware1/Part_1,_\u201cAbend-AID_Receive_From_Network_(RFN)_Installation"},"subpages":{"page":{"@id":"2060","@guid":"9fb28afee653473689d1be78ac6783d4","@draft.state":"inactive","@href":"https://efm-sandbox.mindtouch.us/@api/deki/pages/2060?redirects=0","@deleted":"false","date.created":"Sat, 04 Mar 2017 10:00:07 GMT","language":"en-US","namespace":"main","path":{"@seo":"true","#text":"Compuware1/Part_1,_\u201cAbend-AID_Receive_From_Network_(RFN)_Installation/Chapter_1._\tReceive_From_Network_(RFN)_Installation"},"subpages":{"page":[{"@id":"2065","@guid":"9b4a685ebde744b1812c3e3cb73bb2f7","@draft.state":"inactive","@href":"https://efm-sandbox.mindtouch.us/@api/deki/pages/2065?redirects=0","@deleted":"false","date.created":"Sat, 04 Mar 2017 10:04:07 GMT","language":"en-US","namespace":"main","path":{"@seo":"true","#text":"Compuware1/Part_1,_\u201cAbend-AID_Receive_From_Network_(RFN)_Installation/Chapter_1._\tReceive_From_Network_(RFN)_Installation/Installation_Checklists"},"subpages":{"page":[{"@id":"2070","@guid":"632309e1bb144cd292b1d4376135fa6e","@draft.state":"inactive","@href":"https://efm-sandbox.mindtouch.us/@api/deki/pages/2070?redirects=0","@deleted":"false","date.created":"Sat, 04 Mar 2017 10:18:10 GMT","language":"en-US","namespace":"main","path":{"@seo":"true","#text":"Compuware1/Part_1,_\u201cAbend-AID_Receive_From_Network_(RFN)_Installation/Chapter_1._\tReceive_From_Network_(RFN)_Installation/Installation_Checklists/Configuration_Checklist"},"subpages":"","title":"Configuration Checklist","uri.ui":"https://efm-sandbox.mindtouch.us/Compuware1/Part_1%2C_%E2%80%9CAbend-AID_Receive_From_Network_(RFN)_Installation/Chapter_1._%09Receive_From_Network_(RFN)_Installation/Installation_Checklists/Configuration_Checklist"},{"@id":"2073","@guid":"6f7563ab27574e299a4fcadfe953a3e0","@draft.state":"inactive","@href":"https://efm-sandbox.mindtouch.us/@api/deki/pages/2073?redirects=0","@deleted":"false","date.created":"Sat, 04 Mar 2017 10:26:08 GMT","language":"en-US","namespace":"main","path":{"@seo":"true","#text":"Compuware1/Part_1,_\u201cAbend-AID_Receive_From_Network_(RFN)_Installation/Chapter_1._\tReceive_From_Network_(RFN)_Installation/Installation_Checklists/Customization_Checklist"},"subpages":"","title":"Customization Checklist","uri.ui":"https://efm-sandbox.mindtouch.us/Compuware1/Part_1%2C_%E2%80%9CAbend-AID_Receive_From_Network_(RFN)_Installation/Chapter_1._%09Receive_From_Network_(RFN)_Installation/Installation_Checklists/Customization_Checklist"},{"@id":"2068","@guid":"43bc88ae7a80439f9af4c39116f838a2","@draft.state":"inactive","@href":"https://efm-sandbox.mindtouch.us/@api/deki/pages/2068?redirects=0","@deleted":"false","date.created":"Sat, 04 Mar 2017 10:08:08 GMT","language":"en-US","namespace":"main","path":{"@seo":"true","#text":"Compuware1/Part_1,_\u201cAbend-AID_Receive_From_Network_(RFN)_Installation/Chapter_1._\tReceive_From_Network_(RFN)_Installation/Installation_Checklists/SMP//E_Installation_Checklist"},"subpages":"","title":"SMP/E Installation Checklist","uri.ui":"https://efm-sandbox.mindtouch.us/Compuware1/Part_1%2C_%E2%80%9CAbend-AID_Receive_From_Network_(RFN)_Installation/Chapter_1._%09Receive_From_Network_(RFN)_Installation/Installation_Checklists/SMP%2F%2FE_Installation_Checklist"}]},"title":"Installation Checklists","uri.ui":"https://efm-sandbox.mindtouch.us/Compuware1/Part_1%2C_%E2%80%9CAbend-AID_Receive_From_Network_(RFN)_Installation/Chapter_1._%09Receive_From_Network_(RFN)_Installation/Installation_Checklists"},{"@id":"2063","@guid":"346bc1a438cd40c8be3c2169f6a77cfe","@draft.state":"inactive","@href":"https://efm-sandbox.mindtouch.us/@api/deki/pages/2063?redirects=0","@deleted":"false","date.created":"Sat, 04 Mar 2017 10:01:59 GMT","language":"en-US","namespace":"main","path":{"@seo":"true","#text":"Compuware1/Part_1,_\u201cAbend-AID_Receive_From_Network_(RFN)_Installation/Chapter_1._\tReceive_From_Network_(RFN)_Installation/Step_1._Complete_the_SMP//E_Installation"},"subpages":"","title":"Step 1. Complete the SMP/E Installation","uri.ui":"https://efm-sandbox.mindtouch.us/Compuware1/Part_1%2C_%E2%80%9CAbend-AID_Receive_From_Network_(RFN)_Installation/Chapter_1._%09Receive_From_Network_(RFN)_Installation/Step_1._Complete_the_SMP%2F%2FE_Installation"},{"@id":"2076","@guid":"42a7c6e520b24a3a866cefdf8447c528","@draft.state":"inactive","@href":"https://efm-sandbox.mindtouch.us/@api/deki/pages/2076?redirects=0","@deleted":"false","date.created":"Sat, 04 Mar 2017 10:27:49 GMT","language":"en-US","namespace":"main","path":{"@seo":"true","#text":"Compuware1/Part_1,_\u201cAbend-AID_Receive_From_Network_(RFN)_Installation/Chapter_1._\tReceive_From_Network_(RFN)_Installation/What\u2019s_Next?"},"subpages":"","title":"What\u2019s Next?","uri.ui":"https://efm-sandbox.mindtouch.us/Compuware1/Part_1%2C_%E2%80%9CAbend-AID_Receive_From_Network_(RFN)_Installation/Chapter_1._%09Receive_From_Network_(RFN)_Installation/What%E2%80%99s_Next%3F"}]},"title":"Chapter 1. \tReceive From Network (RFN) Installation","uri.ui":"https://efm-sandbox.mindtouch.us/Compuware1/Part_1%2C_%E2%80%9CAbend-AID_Receive_From_Network_(RFN)_Installation/Chapter_1._%09Receive_From_Network_(RFN)_Installation"}},"title":"Part 1, \u201cAbend-AID Receive From Network (RFN) Installation","uri.ui":"https://efm-sandbox.mindtouch.us/Compuware1/Part_1%2C_%E2%80%9CAbend-AID_Receive_From_Network_(RFN)_Installation"}]},"title":"Compuware1","uri.ui":"https://efm-sandbox.mindtouch.us/Compuware1"}}