[{"PageId":"0","PageLevel":0,"PageOrder":"0","PageParentId":"-1","PageName":"About this guide"},{"PageId":"1","PageLevel":0,"PageOrder":"1","PageParentId":"-1","PageName":"Meet Surface Pro 4"},{"PageId":"2","PageLevel":0,"PageOrder":"2","PageParentId":"-1","PageName":"Set up your Surface Pro 4","children":[{"PageId":"3","PageLevel":1,"PageOrder":"3","PageParentId":"2","PageName":"Charge your Surface Pro 4"},{"PageId":"4","PageLevel":1,"PageOrder":"4","PageParentId":"2","PageName":"Connect the Cover"},{"PageId":"5","PageLevel":1,"PageOrder":"5","PageParentId":"2","PageName":"Set up your Surface Pro 4"}]},{"PageId":"6","PageLevel":0,"PageOrder":"6","PageParentId":"-1","PageName":"The basics","children":[{"PageId":"7","PageLevel":1,"PageOrder":"7","PageParentId":"6","PageName":"Power and charging","children":[{"PageId":"8","PageLevel":2,"PageOrder":"8","PageParentId":"7","PageName":"Check the battery level"},{"PageId":"9","PageLevel":2,"PageOrder":"9","PageParentId":"7","PageName":"Make your battery last"}]},{"PageId":"10","PageLevel":1,"PageOrder":"10","PageParentId":"6","PageName":"Touch, keyboard, pen, and mouse"}]},{"PageId":"11","PageLevel":0,"PageOrder":"11","PageParentId":"-1","PageName":"Keep your Surface up to date"},{"PageId":"12","PageLevel":0,"PageOrder":"12","PageParentId":"-1","PageName":"Get online"},{"PageId":"15","PageLevel":0,"PageOrder":"15","PageParentId":"-1","PageName":"Accounts and signing in","children":[{"PageId":"16","PageLevel":1,"PageOrder":"16","PageParentId":"15","PageName":"Use the sign-in screen"},{"PageId":"17","PageLevel":1,"PageOrder":"17","PageParentId":"15","PageName":"Use Windows Hello to sign in"},{"PageId":"18","PageLevel":1,"PageOrder":"18","PageParentId":"15","PageName":"Sign out"}]},{"PageId":"19","PageLevel":0,"PageOrder":"19","PageParentId":"-1","PageName":"Get to know Windows 10","children":[{"PageId":"20","PageLevel":1,"PageOrder":"20","PageParentId":"19","PageName":"Go to Start"},{"PageId":"21","PageLevel":1,"PageOrder":"21","PageParentId":"19","PageName":"Action center"},{"PageId":"22","PageLevel":1,"PageOrder":"22","PageParentId":"19","PageName":"Task view and virtual desktops"},{"PageId":"23","PageLevel":1,"PageOrder":"23","PageParentId":"19","PageName":"Settings"}]},{"PageId":"24","PageLevel":0,"PageOrder":"24","PageParentId":"-1","PageName":"Type Cover for Surface Pro 4 keyboard and touchpad"},{"PageId":"25","PageLevel":0,"PageOrder":"25","PageParentId":"-1","PageName":"Storage and OneDrive","children":[{"PageId":"26","PageLevel":1,"PageOrder":"26","PageParentId":"25","PageName":"OneDrive","children":[{"PageId":"27","PageLevel":2,"PageOrder":"27","PageParentId":"26","PageName":"Save files you’re working on to OneDrive"}]}]},{"PageId":"28","PageLevel":0,"PageOrder":"28","PageParentId":"-1","PageName":"Surface Pen and OneNote","children":[{"PageId":"29","PageLevel":1,"PageOrder":"29","PageParentId":"28","PageName":"Surface Pen features"},{"PageId":"30","PageLevel":1,"PageOrder":"30","PageParentId":"28","PageName":"Pair the pen with your Surface"},{"PageId":"31","PageLevel":1,"PageOrder":"31","PageParentId":"28","PageName":"Try out features built in to the top button of the pen"},{"PageId":"35","PageLevel":1,"PageOrder":"35","PageParentId":"28","PageName":"Get acquainted with OneNote","children":[{"PageId":"36","PageLevel":2,"PageOrder":"36","PageParentId":"35","PageName":"Send a page or share a notebook"}]}]},{"PageId":"37","PageLevel":0,"PageOrder":"37","PageParentId":"-1","PageName":"Connect monitors, accessories, and other devices","children":[{"PageId":"38","PageLevel":1,"PageOrder":"38","PageParentId":"37","PageName":"Set up your workspace with Surface Dock"},{"PageId":"39","PageLevel":1,"PageOrder":"39","PageParentId":"37","PageName":"Connect or project to a monitor, screen, or other display"}]},{"PageId":"40","PageLevel":0,"PageOrder":"40","PageParentId":"-1","PageName":"Cameras and the Camera app","children":[{"PageId":"41","PageLevel":1,"PageOrder":"41","PageParentId":"40","PageName":"View photos and videos"}]},{"PageId":"42","PageLevel":0,"PageOrder":"42","PageParentId":"-1","PageName":"Apps on your Surface Pro 4","children":[{"PageId":"43","PageLevel":1,"PageOrder":"43","PageParentId":"42","PageName":"The Surface app"},{"PageId":"44","PageLevel":1,"PageOrder":"44","PageParentId":"42","PageName":"Get more apps"}]},{"PageId":"45","PageLevel":0,"PageOrder":"45","PageParentId":"-1","PageName":"Personalization and settings","children":[{"PageId":"46","PageLevel":1,"PageOrder":"46","PageParentId":"45","PageName":"Windows Settings"},{"PageId":"47","PageLevel":1,"PageOrder":"47","PageParentId":"45","PageName":"Cortana"},{"PageId":"48","PageLevel":1,"PageOrder":"48","PageParentId":"45","PageName":"Surface app"},{"PageId":"49","PageLevel":1,"PageOrder":"49","PageParentId":"45","PageName":"Sync your settings"},{"PageId":"50","PageLevel":1,"PageOrder":"50","PageParentId":"45","PageName":"Change settings in Windows apps"}]},{"PageId":"51","PageLevel":0,"PageOrder":"51","PageParentId":"-1","PageName":"Accessibility","children":[{"PageId":"52","PageLevel":1,"PageOrder":"52","PageParentId":"51","PageName":"Ease of Access options for Surface"},{"PageId":"53","PageLevel":1,"PageOrder":"53","PageParentId":"51","PageName":"Other options"},{"PageId":"54","PageLevel":1,"PageOrder":"54","PageParentId":"51","PageName":"Customize the sign-in screen"}]},{"PageId":"55","PageLevel":0,"PageOrder":"55","PageParentId":"-1","PageName":"Care and cleaning","children":[{"PageId":"56","PageLevel":1,"PageOrder":"56","PageParentId":"55","PageName":"Touchscreen care"},{"PageId":"57","PageLevel":1,"PageOrder":"57","PageParentId":"55","PageName":"Cover and keyboard care"},{"PageId":"58","PageLevel":1,"PageOrder":"58","PageParentId":"55","PageName":"Power cord care"}]},{"PageId":"59","PageLevel":0,"PageOrder":"59","PageParentId":"-1","PageName":"Registration, repair, and warranty","children":[{"PageId":"60","PageLevel":1,"PageOrder":"60","PageParentId":"59","PageName":"Register your Surface"},{"PageId":"61","PageLevel":1,"PageOrder":"61","PageParentId":"59","PageName":"Repair"},{"PageId":"62","PageLevel":1,"PageOrder":"62","PageParentId":"59","PageName":"Warranty"},{"PageId":"63","PageLevel":1,"PageOrder":"63","PageParentId":"59","PageName":"Safety and regulatory information"}]},{"PageId":"64","PageLevel":0,"PageOrder":"64","PageParentId":"-1","PageName":"More help"}]